CHANGELOG.md
LICENSE
README.md
fastapi_limiter/__init__.py
fastapi_limiter/depends.py
fastapi_limiter/py.typed
fastapi_limiter_valkey-0.1.1.dist-info/LICENSE
fastapi_limiter_valkey-0.1.1.dist-info/METADATA
fastapi_limiter_valkey-0.1.1.dist-info/WHEEL
fastapi_limiter_valkey-0.1.1.dist-info/RECORD
