Metadata-Version: 2.1
Name: fastapi-limiter-valkey
Version: 0.1.1
Summary: A request rate limiter for fastapi
Home-page: https://github.com/scraiber/fastapi-limiter-valkey
License: Apache2.0
Keywords: fastapi,limiter
Author: Scraiber
Author-email: contact@scraiber.com
Requires-Python: >=3.9,<4.0
Classifier: License :: Other/Proprietary License
Classifier: Programming Language :: Python :: 3
Classifier: Programming Language :: Python :: 3.9
Classifier: Programming Language :: Python :: 3.10
Classifier: Programming Language :: Python :: 3.11
Classifier: Programming Language :: Python :: 3.12
Classifier: Programming Language :: Python :: 3.13
Requires-Dist: fastapi
Requires-Dist: valkey (>=6.0.2)
Project-URL: Documentation, https://github.com/scraiber/fastapi-limiter-valkey
Project-URL: Repository, https://github.com/scraiber/fastapi-limiter-valkey.git
